pyzo/__init__.py
pyzo/__main__.py
pyzo/_start.py
pyzo/pre_qt_import.py
pyzo/codeeditor/__init__.py
pyzo/codeeditor/_test.py
pyzo/codeeditor/base.py
pyzo/codeeditor/highlighter.py
pyzo/codeeditor/license.txt
pyzo/codeeditor/manager.py
pyzo/codeeditor/misc.py
pyzo/codeeditor/qt.py
pyzo/codeeditor/style.py
pyzo/codeeditor/textutils.py
pyzo/codeeditor/extensions/__init__.py
pyzo/codeeditor/extensions/appearance.py
pyzo/codeeditor/extensions/autocompletion.py
pyzo/codeeditor/extensions/behaviour.py
pyzo/codeeditor/extensions/calltip.py
pyzo/codeeditor/parsers/__init__.py
pyzo/codeeditor/parsers/c_parser.py
pyzo/codeeditor/parsers/cython_parser.py
pyzo/codeeditor/parsers/python_parser.py
pyzo/codeeditor/parsers/s_expr_parser.py
pyzo/codeeditor/parsers/tokens.py
pyzo/core/__init__.py
pyzo/core/about.py
pyzo/core/baseTextCtrl.py
pyzo/core/codeparser.py
pyzo/core/commandline.py
pyzo/core/compactTabWidget.py
pyzo/core/editor.py
pyzo/core/editorTabs.py
pyzo/core/history.py
pyzo/core/icons.py
pyzo/core/kernelbroker.py
pyzo/core/main.py
pyzo/core/menu.py
pyzo/core/pdfExport.py
pyzo/core/pyzoLogging.py
pyzo/core/shell.py
pyzo/core/shellInfoDialog.py
pyzo/core/shellStack.py
pyzo/core/splash.py
pyzo/core/statusbar.py
pyzo/core/themeEdit.py
pyzo/pyzokernel/__init__.py
pyzo/pyzokernel/_nope.py
pyzo/pyzokernel/debug.py
pyzo/pyzokernel/guiintegration.py
pyzo/pyzokernel/interpreter.py
pyzo/pyzokernel/introspection.py
pyzo/pyzokernel/magic.py
pyzo/pyzokernel/pipper.py
pyzo/pyzokernel/start.py
pyzo/qt/__init__.py
pyzo/qt/qtutils.py
pyzo/resources/defaultConfig.ssdf
pyzo/resources/org.pyzo.Pyzo.desktop
pyzo/resources/tutorial.py
pyzo/resources/appicons/py.icns
pyzo/resources/appicons/py.ico
pyzo/resources/appicons/pyzologo.icns
pyzo/resources/appicons/pyzologo.ico
pyzo/resources/appicons/pyzologo128.bmp
pyzo/resources/appicons/pyzologo128.png
pyzo/resources/appicons/pyzologo16.png
pyzo/resources/appicons/pyzologo256.png
pyzo/resources/appicons/pyzologo32.png
pyzo-4.20.0.dist-info/entry_points.txt
pyzo-4.20.0.dist-info/licenses/LICENSE.md
pyzo-4.20.0.dist-info/WHEEL
pyzo-4.20.0.dist-info/METADATA
pyzo-4.20.0.dist-info/RECORD
