Metadata-Version: 2.4
Name: pyzo
Version: 4.20.0
Summary: the Python IDE for scientific computing
Keywords: interactive,IDE,Qt,science,computing
Author: the Pyzo development team
Requires-Python: >= 3.6
License-File: LICENSE.md
Requires-Dist: pyzo[lint, tests] ; extra == "dev"
Requires-Dist: ruff ; extra == "lint"
Requires-Dist: pytest ; extra == "tests"
Project-URL: Documentation, https://pyzo.org
Project-URL: Homepage, https://pyzo.org
Project-URL: Repository, https://github.com/pyzo/pyzo
Provides-Extra: dev
Provides-Extra: lint
Provides-Extra: tests
